{"anime":[{"sailormoon":2195},{"inuyasha":3129},{"cardcaptorsakura":255},{"bleach":5728},{"princeoftennis":459},{"naruto":51341},{"fruitsbasket":1246},{"fullmetalalchemist":2041},{"souleater":5308},{"fairytail":42462},{"blueexorcist":2294},{"hetalia":27195},{"madokamagica":731},{"rwby":20482},{"jjba":6584},{"attackontitan":24512},{"mha":91127},{"haikyuu":45410},{"yurionice":4708},{"spyxfamily":1133},{"swordartonline":3184},{"ohshc":5721},{"assassinationclassroom":4107},{"kny":12351},{"bsd":8913},{"gundam":1060},{"dandadan":179},{"apothecarydiaries":91}],"cartoon":[{"mlp":12865},{"voltron":14517},{"vld":3375},{"daria":187},{"powerpuffgirls":907},{"invaderzim":1648},{"kimpossible":411},{"teentitans":4416},{"dannyphantom":3234},{"atla":4007},{"lok":982},{"totaldrama":5148},{"gravityfalls":13441},{"stevenuniverse":11571},{"miraculousladybug":12984},{"svtfoe":2339},{"shera":1482},{"hazbinhotel":10311},{"transformers":12605},{"helluvaboss":4089},{"arcane":2794}],"tv":[{"supernatural winchester":22149},{"doctorwho":14135},{"sherlock":13798},{"startrek":2688},{"glee":7982},{"ouat":8851},{"buffy":839},{"merlin":6360},{"stargate":421},{"teenwolf":27503},{"thewalkingdead":12540},{"xfiles":211},{"agentsofshield":2237},{"agentcarter":482},{"daredevil":1437},{"jessicajones":268},{"wandavision":915},{"heatedrivalry":211},{"bridgerton":1637}],"game":[{"legendofzelda":3715},{"sonic":16028},{"pokemon":37731},{"finalfantasy":2073},{"kingdomhearts":3205},{"persona":2458},{"fireemblem":2679},{"leagueoflegends":2895},{"dragonage":933},{"minecraft":37209},{"danganronpa":31029},{"fnaf":45946},{"undertale":43795},{"mysticmessenger":3476},{"overwatch":5218},{"genshinimpact":21891},{"honkaiimpact3rd":793},{"honkai":1596},{"honkaistarrail":1768},{"zenlesszonezero":396},{"projectsekai":3021},{"ensemblestars":470},{"umamusume":272},{"deltarune":2968}],"bandom":[{"onedirection":112859},{"mychemicalromance":10929},{"panicatthedisco":6842},{"falloutboy":6150},{"twentyonepilots":12555},{"taylorswift":11254},{"bandom":941},{"nsync":163},{"thebeatles":2789}],"kpop":[{"Kpop":141380},{"bts":245703},{"exo":45591},{"shinee":5195},{"redvelvet":11656},{"twice":21942},{"blackpink":35595},{"nct":31779},{"straykids":39352},{"seventeen":25776},{"txt":15042},{"got7":20952},{"monstax":6999},{"loona":3733},{"superjunior":2553}],"movie":[{"starwars":24291},{"avengers":52383},{"thor":18668},{"captainamerica":21362},{"guardiansofthegalaxy":1820},{"marvel":69810},{"kpopdemonhunters":1572}],"book":[{"lotr":4873},{"thehobbit":2937},{"silmarillion":329},{"gameofthrones":5682},{"harrypotter":142156},{"warriorcats":24742},{"pjo":21467},{"hoo":12488},{"twilight":26310},{"hungergames":13843},{"phantomoftheopera":1523},{"mdzs":2633},{"orv":836},{"goodomens":1917},{"thekingsavatar":49},{"maximumride":883},{"narnia":4183},{"divergent":9856},{"vampireacademy":1482},{"asoue":926},{"aftg":148}],"misc":[{"vocaloid":8024},{"homestuck":12295},{"hamilton":16955},{"danandphil":9003},{"wwe":9900},{"roosterteeth":1741},{"youtube":51616},{"welcometonightvale":293},{"lesmiserables":850},{"hermitcraft":3746},{"dreamsmp":27789},{"hololive":1282},{"tadc":1846}]}